utils/__init__.py
utils/demo.py
banxx-0.0.1.dist-info/LICENSE
banxx-0.0.1.dist-info/METADATA
banxx-0.0.1.dist-info/WHEEL
banxx-0.0.1.dist-info/top_level.txt
banxx-0.0.1.dist-info/RECORD
